LICENSE
MANIFEST.in
README.rst
getline.c
getline.h
setup.cfg
setup.py
sizeop.h
ttyprompt.c
ttyprompt.h
TTYprompt.egg-info/PKG-INFO
TTYprompt.egg-info/SOURCES.txt
TTYprompt.egg-info/dependency_links.txt
TTYprompt.egg-info/top_level.txt
ttyprompt/__init__.py
ttyprompt/tty.c
ttyprompt/ttyprompt.py