Metadata-Version: 1.1
Name: TTYprompt
Version: 0.2
Summary: TTYprompt reads a line of text from the terminal.
Home-page: https://bitbucket.org/eliteraspberries/ttyprompt
Author: Mansour Moufid
Author-email: mansourmoufid@gmail.com
License: ISC
Platform: UNKNOWN
Classifier: Development Status :: 4 - Beta
Classifier: Intended Audience :: Developers
Classifier: License :: OSI Approved :: ISC License (ISCL)
Classifier: Operating System :: OS Independent
Classifier: Programming Language :: C
Classifier: Programming Language :: Python
Classifier: Topic :: Scientific/Engineering :: Mathematics
